doradetector/__init__.py
doradetector/doradetector.py
doradetector-1.0.1.dist-info/AUTHORS.rst
doradetector-1.0.1.dist-info/LICENSE
doradetector-1.0.1.dist-info/METADATA
doradetector-1.0.1.dist-info/WHEEL
doradetector-1.0.1.dist-info/top_level.txt
doradetector-1.0.1.dist-info/RECORD
