Metadata-Version: 2.1
Name: doradetector
Version: 1.0.1
Summary: Python package to detect when ETB emits Doraemon
Home-page: https://github.com/erral/doradetector
Author: Mikel Larreategi
Author-email: mlarreategi@codesyntax.com
License: GNU General Public License v3
Keywords: doradetector
Platform: UNKNOWN
Classifier: Development Status :: 2 - Pre-Alpha
Classifier: Intended Audience :: Developers
Classifier: License :: OSI Approved :: GNU General Public License v3 (GPLv3)
Classifier: Natural Language :: English
Classifier: Programming Language :: Python :: 3
Classifier: Programming Language :: Python :: 3.6
Classifier: Programming Language :: Python :: 3.7
Classifier: Programming Language :: Python :: 3.8
Requires-Python: >=3.6
Requires-Dist: beautifulsoup4 (==4.10.0)
Requires-Dist: certifi (==2021.10.8)
Requires-Dist: charset-normalizer (==2.0.10)
Requires-Dist: idna (==3.3)
Requires-Dist: requests (==2.27.1)
Requires-Dist: soupsieve (==2.3.1)
Requires-Dist: urllib3 (==1.26.7)
